testchimp_local/.env.prod
testchimp_local/.env.staging
testchimp_local/__init__.py
testchimp_local/agent_runner.py
testchimp_local/agent_utils.py
testchimp_local/browser_context.py
testchimp_local/chrome_ext_bridge.py
testchimp_local/cli.py
testchimp_local/config_help.py
testchimp_local/console_watcher.py
testchimp_local/datas.py
testchimp_local/explore_runner.py
testchimp_local/feature_facade.py
testchimp_local/html_utils.py
testchimp_local/main.py
testchimp_local/network_utils.py
testchimp_local/network_watcher.py
testchimp_local/openai_facade.py
testchimp_local/server.py
testchimp_local/version.py
testchimp_local/web_utils.py
testchimp_local-0.0.9.dist-info/METADATA
testchimp_local-0.0.9.dist-info/WHEEL
testchimp_local-0.0.9.dist-info/entry_points.txt
testchimp_local-0.0.9.dist-info/top_level.txt
testchimp_local-0.0.9.dist-info/RECORD
