Metadata-Version: 2.4
Name: testchimp-local
Version: 0.0.9
Summary: Autonomous exploratory testing - right from your CLI
Author-email: TestChimp <nuwansam@testchimp.io>
Requires-Python: <4.0,>=3.11
Requires-Dist: fastapi==0.115.13
Requires-Dist: uvicorn==0.34.3
Requires-Dist: python-dotenv==1.1.1
Requires-Dist: playwright==1.52.0
Requires-Dist: torch==2.7.1
Requires-Dist: sentence-transformers==4.1.0
Requires-Dist: faiss-cpu==1.11.0
Requires-Dist: mem0ai==0.1.111
Requires-Dist: tenacity==8.5.0
Requires-Dist: browser-use==0.4.2
Requires-Dist: packaging<25,>=23.2
Requires-Dist: fastmcp
Requires-Dist: openai==1.91.0
